ptitprince/PtitPrince.py
ptitprince/__init__.py
ptitprince-0.2.6.dist-info/LICENSE
ptitprince-0.2.6.dist-info/METADATA
ptitprince-0.2.6.dist-info/WHEEL
ptitprince-0.2.6.dist-info/top_level.txt
ptitprince-0.2.6.dist-info/RECORD
