Metadata-Version: 2.1
Name: ptitprince
Version: 0.2.6
Summary: A Python implementation of Rainclouds, originally on R, ggplot2. Written on top of seaborn.
Home-page: https://github.com/pog87/PtitPrince
Author: Davide Poggiali
Author-email: davide.poggiali@unipd.it
License: MIT
Keywords: data visualization,raincloud plots
Classifier: Intended Audience :: Science/Research
Classifier: Intended Audience :: Developers
Classifier: License :: OSI Approved
Classifier: Programming Language :: Python
Classifier: Topic :: Software Development
Classifier: Topic :: Scientific/Engineering
Classifier: Operating System :: Microsoft :: Windows
Classifier: Operating System :: POSIX
Classifier: Operating System :: Unix
Classifier: Operating System :: MacOS
License-File: LICENSE
